poetry_incr_version/__init__.py
poetry_incr_version/__main__.py
poetry_incr_version/_errors.py
poetry_incr_version/_file.py
poetry_incr_version/_pyproject.py
poetry_incr_version/_version.py
poetry_incr_version/py.typed
poetry_incr_version/util.py
poetry_incr_version-0.1.9.dist-info/LICENSE
poetry_incr_version-0.1.9.dist-info/METADATA
poetry_incr_version-0.1.9.dist-info/WHEEL
poetry_incr_version-0.1.9.dist-info/entry_points.txt
poetry_incr_version-0.1.9.dist-info/RECORD
