Metadata-Version: 2.1
Name: poetry-incr-version
Version: 0.1.9
Summary: Tool to help manage the version of a Poetry project.
License: MIT
Author: Florian Daude
Author-email: floriandaude@hotmail.fr
Requires-Python: >=3.11
Classifier: License :: OSI Approved :: MIT License
Classifier: Programming Language :: Python :: 3
Classifier: Programming Language :: Python :: 3.11
Classifier: Programming Language :: Python :: 3.12
